cmpitool/__init__.py
cmpitool/add_masks.py
cmpitool/calculate_errors.py
cmpitool/calculate_fractions.py
cmpitool/cmpisetup.py
cmpitool/cmpitool.py
cmpitool/config_cmip6.py
cmpitool/loading_models.py
cmpitool/loading_obs.py
cmpitool/plotting_biasmaps.py
cmpitool/plotting_heatmaps.py
cmpitool/read_errors.py
cmpitool/write_errors.py
cmpitool/write_fractions.py
cmpitool/data/ocean_basins.geojson
cmpitool-1.2.dist-info/licenses/LICENCE
cmpitool-1.2.dist-info/METADATA
cmpitool-1.2.dist-info/WHEEL
cmpitool-1.2.dist-info/top_level.txt
cmpitool-1.2.dist-info/RECORD
