Metadata-Version: 2.4
Name: cmpitool
Version: 1.2
Summary: cmpitool
Home-page: https://github.com/JanStreffing/cmpitool
Download-URL: https://github.com/JanStreffing/cmpitool/archive/refs/tags/v1.2.tar.gz
Author: Jan Streffing
Author-email: j.streffing1988@gmail.com
License: MIT license
Keywords: cmpitool
Classifier: Development Status :: 2 - Pre-Alpha
Classifier: Intended Audience :: Developers
Classifier: License :: OSI Approved :: MIT License
Classifier: Natural Language :: English
Classifier: Programming Language :: Python :: 3
Classifier: Programming Language :: Python :: 3.9
License-File: LICENCE
Requires-Dist: geopandas
Requires-Dist: matplotlib
Requires-Dist: netCDF4>=1.6.0
Requires-Dist: numpy
Requires-Dist: pandas>=1.0.0
Requires-Dist: pooch
Requires-Dist: regionmask
Requires-Dist: seaborn
Requires-Dist: tqdm
Requires-Dist: xarray
Dynamic: author
Dynamic: author-email
Dynamic: classifier
Dynamic: description
Dynamic: download-url
Dynamic: home-page
Dynamic: keywords
Dynamic: license
Dynamic: license-file
Dynamic: requires-dist
Dynamic: summary
